ovos_tts_plugin_mimic2/__init__.py
ovos_tts_plugin_mimic2/version.py
ovos_tts_plugin_mimic2-0.1.5.dist-info/LICENSE
ovos_tts_plugin_mimic2-0.1.5.dist-info/METADATA
ovos_tts_plugin_mimic2-0.1.5.dist-info/WHEEL
ovos_tts_plugin_mimic2-0.1.5.dist-info/entry_points.txt
ovos_tts_plugin_mimic2-0.1.5.dist-info/top_level.txt
ovos_tts_plugin_mimic2-0.1.5.dist-info/zip-safe
ovos_tts_plugin_mimic2-0.1.5.dist-info/RECORD
